typedtree/__init__.py
typedtree/node.py
typedtree/traversalmode.py
typedtree/tree.py
typedtree/version.py
typed_tree-1.0.8.dist-info/LICENSE
typed_tree-1.0.8.dist-info/METADATA
typed_tree-1.0.8.dist-info/WHEEL
typed_tree-1.0.8.dist-info/top_level.txt
typed_tree-1.0.8.dist-info/RECORD
