Metadata-Version: 2.1
Name: typed-tree
Version: 1.0.8
Summary: TypedTree provides a tree structure that allows adding type information to its nodes and edges, respectively
Home-page: https://github.com/brettkromkamp/typed-tree
Author: Brett Alistair Kromkamp
Author-email: brettkromkamp@gmail.com
Project-URL: Bug Tracker, https://github.com/brettkromkamp/typed-tree/issues
Classifier: Development Status :: 5 - Production/Stable
Classifier: Intended Audience :: Developers
Classifier: License :: OSI Approved :: MIT License
Classifier: Natural Language :: English
Classifier: Programming Language :: Python :: 3.7
Classifier: Programming Language :: Python :: 3.8
Classifier: Programming Language :: Python :: 3.9
Classifier: Programming Language :: Python :: 3.10
Classifier: Programming Language :: Python :: Implementation :: CPython
Classifier: Topic :: Software Development :: Libraries :: Python Modules
Requires-Python: >=3.7
License-File: LICENSE
